Direct_Download.py
Direct_Download-0.4.4.dist-info/LICENSE
Direct_Download-0.4.4.dist-info/METADATA
Direct_Download-0.4.4.dist-info/WHEEL
Direct_Download-0.4.4.dist-info/top_level.txt
Direct_Download-0.4.4.dist-info/RECORD
