Metadata-Version: 2.1
Name: Direct-Download
Version: 0.4.4
Summary: A Direct Downloader Module Which Will Get Direct Download Link From Some Popular File Uploading Websites Like Mediafire, Anonfiles
Home-page: https://github.com/CYCNO/DirectDownload
Author: CYCNO
Keywords: direct download,anonfiles,mediafire,mediafire direct download,anonfiles direct download,google drive,google drive direct download link,google drive download link,megaupload,myfile,letsupload,filechan
Classifier: Programming Language :: Python :: 3
Classifier: License :: OSI Approved :: MIT License
Classifier: Operating System :: OS Independent
Requires-Python: >=3.6
License-File: LICENSE
Requires-Dist: wget
Requires-Dist: requests
